<?xml version="1.0" encoding="UTF-8"?>
<QCARConfig xmlns:xsi="http://www.w3.org/2001/XMLSchema-instance" xsi:noNamespaceSchemaLocation="qcar_config.xsd">
  <Tracking>
    <ImageTarget name="USB_QR" size="0.060000 0.060000" />
    <ImageTarget name="OPS_QR" size="0.060000 0.060000" />
    <ImageTarget name="HDD_QR" size="0.060000 0.060000" />
    <ImageTarget name="KingOfClubs" size="0.060000 0.088525" />
    <ImageTarget name="JackOfSpades" size="0.060000 0.092252" />
    <ImageTarget name="QueenOfHearts" size="0.060000 0.089400" />
  </Tracking>
</QCARConfig>
